[
  {
    "key": "MMG3M9FR",
    "version": 38,
    "itemType": "journalArticle",
    "title": "Code review in digital humanities",
    "creators": [
      {
        "creatorType": "author",
        "firstName": "Julia",
        "lastName": "Damerow"
      },
      {
        "creatorType": "author",
        "firstName": "Rebecca Sutton",
        "lastName": "Koeser"
      },
      {
        "creatorType": "author",
        "firstName": "Jeffrey C",
        "lastName": "Carver"
      },
      {
        "creatorType": "author",
        "firstName": "Malte",
        "lastName": "Vogl"
      }
    ],
    "abstractNote": "Software and computational methods offer tremendous possibilities for digital humanities research, both accelerating existing work and opening up entirely new questions. However, software also has the potential to introduce new kinds of errors into the research workflow. How do we know that the software developed for a digital humanities project is error free and does what we think it does? Code review is a widespread technique to improve software quality and reduce the number of flaws, where a programmer other than the author reviews and comments on the source code. However, given that many digital humanities developers work in developer teams of one, code review is often not possible. In this article, we share progress and insights from an effort to establish a community code review process for digital humanities, and provide background to help understand the need and potential impacts of this work.",
    "publicationTitle": "Digital Scholarship in the Humanities",
    "volume": "40",
    "issue": "Supplement_1",
    "pages": "i18-i26",
    "date": "2024",
    "series": "",
    "seriesTitle": "",
    "seriesText": "",
    "journalAbbreviation": "Digital Scholarship in the Humanities",
    "language": "",
    "DOI": "10.1093/llc/fqae052",
    "ISSN": "2055-7671",
    "shortTitle": "",
    "url": "https://doi.org/10.1093/llc/fqae052",
    "accessDate": "2025-03-18T20:42:11Z",
    "archive": "",
    "archiveLocation": "",
    "libraryCatalog": "Silverchair",
    "callNumber": "",
    "rights": "",
    "extra": "",
    "tags": [],
    "collections": [],
    "relations": {},
    "dateAdded": "2025-03-18T20:42:11Z",
    "dateModified": "2025-03-18T20:44:00Z"
  },
  {
    "key": "V8QY345W",
    "version": 36,
    "parentItem": "MMG3M9FR",
    "itemType": "attachment",
    "linkMode": "imported_url",
    "title": "Snapshot",
    "accessDate": "2025-03-18T20:42:18Z",
    "url": "https://academic.oup.com/dsh/article/40/Supplement_1/i18/7796890?login=false",
    "note": "",
    "contentType": "text/html",
    "charset": "utf-8",
    "filename": "7796890.html",
    "md5": "1d09659aae75d2cf4d74d83318ac2c20",
    "mtime": 1742330538000,
    "tags": [],
    "relations": {},
    "dateAdded": "2025-03-18T20:42:18Z",
    "dateModified": "2025-03-18T20:42:18Z"
  },
  {
    "key": "HV7WZSS5",
    "version": 35,
    "parentItem": "MMG3M9FR",
    "itemType": "attachment",
    "linkMode": "imported_url",
    "title": "Full Text PDF",
    "accessDate": "2025-03-18T20:42:13Z",
    "url": "https://academic.oup.com/dsh/article-pdf/40/Supplement_1/i18/59462432/fqae052.pdf",
    "note": "",
    "contentType": "application/pdf",
    "charset": "",
    "filename": "Damerow et al. - 2025 - Code review in digital humanities.pdf",
    "md5": "2c02c5de73821678861714b3f4f6d560",
    "mtime": 1742330533000,
    "tags": [],
    "relations": {},
    "dateAdded": "2025-03-18T20:42:13Z",
    "dateModified": "2025-03-18T20:42:13Z"
  },
  {
    "key": "G2VJLQ7S",
    "version": 31,
    "parentItem": "CW6UJWTJ",
    "itemType": "attachment",
    "linkMode": "imported_url",
    "title": "arXiv.org Snapshot",
    "accessDate": "2024-08-21T19:33:34Z",
    "url": "http://arxiv.org/abs/1407.5648",
    "note": "",
    "contentType": "text/html",
    "charset": "utf-8",
    "filename": "1407.html",
    "md5": "203fd32b47731e2eaebcaa772ed26c41",
    "mtime": 1724268814000,
    "tags": [],
    "relations": {},
    "dateAdded": "2024-08-21T19:33:34Z",
    "dateModified": "2024-08-21T19:33:34Z"
  },
  {
    "key": "WXGZ3GFL",
    "version": 30,
    "parentItem": "CW6UJWTJ",
    "itemType": "attachment",
    "linkMode": "imported_url",
    "title": "arXiv Fulltext PDF",
    "accessDate": "2024-08-21T19:33:28Z",
    "url": "https://arxiv.org/pdf/1407.5648.pdf",
    "note": "",
    "contentType": "application/pdf",
    "charset": "",
    "filename": "Petre and Wilson - 2014 - Code Review For and By Scientists.pdf",
    "md5": "3515efc88d3d889a3b35aa64ed7d4be0",
    "mtime": 1724268808000,
    "tags": [],
    "relations": {},
    "dateAdded": "2024-08-21T19:33:28Z",
    "dateModified": "2024-08-21T19:33:28Z"
  },
  {
    "key": "JG5VMVFQ",
    "version": 28,
    "parentItem": "CW6UJWTJ",
    "itemType": "note",
    "note": "Comment: 4 pages",
    "tags": [],
    "relations": {},
    "dateAdded": "2024-08-21T19:33:27Z",
    "dateModified": "2024-08-21T19:33:27Z"
  },
  {
    "key": "CW6UJWTJ",
    "version": 28,
    "itemType": "preprint",
    "title": "Code Review For and By Scientists",
    "creators": [
      {
        "creatorType": "author",
        "firstName": "Marian",
        "lastName": "Petre"
      },
      {
        "creatorType": "author",
        "firstName": "Greg",
        "lastName": "Wilson"
      }
    ],
    "abstractNote": "We describe two pilot studies of code review by and for scientists. Our principal findings are that scientists are enthusiastic, but need to be shown code review in action, and that just-in-time review of small code changes is more likely to succeed than large-scale end-of-work reviews.",
    "genre": "",
    "repository": "arXiv",
    "archiveID": "arXiv:1407.5648",
    "place": "",
    "date": "2014-09-07",
    "series": "",
    "seriesNumber": "",
    "DOI": "10.48550/arXiv.1407.5648",
    "citationKey": "",
    "url": "http://arxiv.org/abs/1407.5648",
    "accessDate": "2024-08-21T19:33:27Z",
    "archive": "",
    "archiveLocation": "",
    "shortTitle": "",
    "language": "",
    "libraryCatalog": "arXiv.org",
    "callNumber": "",
    "rights": "",
    "extra": "arXiv:1407.5648 [cs]",
    "tags": [
      {
        "tag": "Computer Science - Software Engineering",
        "type": 1
      }
    ],
    "collections": [
      "VCTP23NU"
    ],
    "relations": {},
    "dateAdded": "2024-08-21T19:33:27Z",
    "dateModified": "2024-08-21T19:33:27Z"
  },
  {
    "key": "HIBB6J3Z",
    "version": 14,
    "parentItem": "XAHXAVQ3",
    "itemType": "note",
    "note": "{\"authors\":[{\"@type\":\"Person\",\"name\":\"Brendan Cleary\",\"uri\":\"\",\"localAuthorityId\":\"\",\"firstName\":\"Brendan\",\"lastName\":\"Cleary\",\"positionInList\":0,\"affiliations\":[]},{\"@type\":\"Person\",\"name\":\"Frederic Painchaud\",\"uri\":\"\",\"localAuthorityId\":\"\",\"firstName\":\"Frederic\",\"lastName\":\"Painchaud\",\"positionInList\":0,\"affiliations\":[]},{\"@type\":\"Person\",\"name\":\"Margaret-Anne Storey\",\"uri\":\"\",\"localAuthorityId\":\"\",\"firstName\":\"Margaret-Anne\",\"lastName\":\"Storey\",\"positionInList\":0,\"affiliations\":[]},{\"@type\":\"Person\",\"name\":\"Daniel German\",\"uri\":\"\",\"localAuthorityId\":\"\",\"firstName\":\"Daniel\",\"lastName\":\"German\",\"positionInList\":0,\"affiliations\":[]},{\"@type\":\"Person\",\"name\":\"Peter Rigby\",\"uri\":\"http://viaf.org/viaf/5201159248257804870009/\",\"localAuthorityId\":\"\",\"firstName\":\"Peter\",\"lastName\":\"Rigby\",\"positionInList\":0,\"affiliations\":[]}],\"editors\":[],\"otherCreators\":[],\"conceptTags\":[],\"references\":null,\"gilesUploads\":null}",
    "tags": [
      {
        "tag": "citesphere-metadata"
      }
    ],
    "relations": {},
    "dateAdded": "2024-02-15T17:41:32Z",
    "dateModified": "2024-02-15T17:41:32Z"
  },
  {
    "key": "XAHXAVQ3",
    "version": 13,
    "itemType": "journalArticle",
    "title": "Contemporary Peer Review in Action: Lessons from Open Source Development",
    "creators": [
      {
        "creatorType": "author",
        "firstName": "Brendan",
        "lastName": "Cleary"
      },
      {
        "creatorType": "author",
        "firstName": "Frederic",
        "lastName": "Painchaud"
      },
      {
        "creatorType": "author",
        "firstName": "Margaret-Anne",
        "lastName": "Storey"
      },
      {
        "creatorType": "author",
        "firstName": "Daniel",
        "lastName": "German"
      },
      {
        "creatorType": "author",
        "firstName": "Peter",
        "lastName": "Rigby"
      }
    ],
    "abstractNote": "",
    "publicationTitle": "IEEE Software",
    "volume": "29",
    "issue": "6",
    "pages": "56-61",
    "date": "11/2012",
    "series": "",
    "seriesTitle": "",
    "seriesText": "",
    "journalAbbreviation": "IEEE Softw.",
    "language": "en",
    "DOI": "10.1109/MS.2012.24",
    "ISSN": "0740-7459",
    "shortTitle": "Contemporary Peer Review in Action",
    "url": "http://ieeexplore.ieee.org/document/6148202/",
    "accessDate": "2023-05-04T21:02:23Z",
    "archive": "",
    "archiveLocation": "",
    "libraryCatalog": "DOI.org (Crossref)",
    "callNumber": "",
    "rights": "",
    "extra": "",
    "tags": [],
    "collections": [
      "VCTP23NU"
    ],
    "relations": {},
    "dateAdded": "2023-05-12T15:21:02Z",
    "dateModified": "2024-02-15T17:41:30Z"
  },
  {
    "key": "K95FKZF3",
    "version": 24,
    "parentItem": "YGKW27DQ",
    "itemType": "attachment",
    "linkMode": "imported_file",
    "title": "Koeser - 2015 - Trusting Others to ‘Do the Math’.pdf",
    "accessDate": "",
    "url": "",
    "note": "",
    "contentType": "application/pdf",
    "charset": "",
    "filename": "Koeser - 2015 - Trusting Others to ‘Do the Math’.pdf",
    "md5": "cb776335905b19399ab2aac9e910fe79",
    "mtime": 1683939512000,
    "tags": [],
    "relations": {},
    "dateAdded": "2023-05-13T00:58:15Z",
    "dateModified": "2023-05-13T00:58:15Z"
  },
  {
    "key": "YGKW27DQ",
    "version": 12,
    "itemType": "journalArticle",
    "title": "Trusting Others to ‘Do the Math’",
    "creators": [
      {
        "creatorType": "author",
        "firstName": "Rebecca Sutton",
        "lastName": "Koeser"
      }
    ],
    "abstractNote": "",
    "publicationTitle": "Interdisciplinary Science Reviews",
    "volume": "40",
    "issue": "4",
    "pages": "376-392",
    "date": "2015-10-02",
    "series": "",
    "seriesTitle": "",
    "seriesText": "",
    "journalAbbreviation": "Interdisciplinary Science Reviews",
    "language": "en",
    "DOI": "10.1080/03080188.2016.1165454",
    "ISSN": "0308-0188, 1743-2790",
    "shortTitle": "",
    "url": "http://www.tandfonline.com/doi/full/10.1080/03080188.2016.1165454",
    "accessDate": "2023-01-16T15:02:33Z",
    "archive": "",
    "archiveLocation": "",
    "libraryCatalog": "DOI.org (Crossref)",
    "callNumber": "",
    "rights": "",
    "extra": "",
    "tags": [],
    "collections": [
      "VCTP23NU"
    ],
    "relations": {},
    "dateAdded": "2023-05-13T00:58:15Z",
    "dateModified": "2023-05-13T00:58:15Z"
  },
  {
    "key": "TZQ9WLX4",
    "version": 27,
    "itemType": "conferencePaper",
    "title": "Track 1 Paper: Surveying the U.S. National Postdoctoral Association Regarding Software Use and Training in Research",
    "creators": [
      {
        "creatorType": "author",
        "firstName": "Udit",
        "lastName": "Nangia"
      },
      {
        "creatorType": "author",
        "firstName": "Daniel S.",
        "lastName": "Katz"
      }
    ],
    "abstractNote": "This paper reports on the results of a 2017 survey conducted by email and web of members of the U.S. National Postdoctoral Association regarding their use of software in research and their training regarding software development. The responses show that that 95% of respondents use research software. Of all the respondents, 63% state they could not do their research without research software, 31% could do it but with more effort, and 6% would not find a significant difference in their research without research software. In addition, 54% of respondents have not received any training in software development, though all respondents who develop software for researchers have received either self-taught or formal software development training.",
    "date": "2017-06-19",
    "proceedingsTitle": "",
    "conferenceName": "",
    "place": "Manchester, UK",
    "publisher": "Zenodo",
    "volume": "",
    "pages": "",
    "series": "",
    "language": "",
    "DOI": "10.5281/zenodo.814220",
    "ISBN": "",
    "shortTitle": "Track 1 Paper",
    "url": "https://zenodo.org/record/814220",
    "accessDate": "2023-05-11T18:49:10Z",
    "archive": "",
    "archiveLocation": "",
    "libraryCatalog": "",
    "callNumber": "",
    "rights": "",
    "extra": "",
    "tags": [
      {
        "tag": "software training",
        "type": 1
      },
      {
        "tag": "software use",
        "type": 1
      },
      {
        "tag": "survey",
        "type": 1
      }
    ],
    "collections": [
      "VCTP23NU"
    ],
    "relations": {},
    "dateAdded": "2023-05-12T15:21:02Z",
    "dateModified": "2023-05-12T15:21:02Z"
  },
  {
    "key": "R2FYXP5M",
    "version": 25,
    "parentItem": "Y3HY74M3",
    "itemType": "attachment",
    "linkMode": "imported_file",
    "title": "Fagan - 1976 - Design and code inspections to reduce errors in pr.pdf",
    "accessDate": "",
    "url": "",
    "note": "",
    "contentType": "application/pdf",
    "charset": "",
    "filename": "Fagan - 1976 - Design and code inspections to reduce errors in pr.pdf",
    "md5": "cb48388a2f624f852ae9287a4c4a5510",
    "mtime": 1683904862000,
    "tags": [],
    "relations": {},
    "dateAdded": "2023-05-12T15:21:02Z",
    "dateModified": "2023-05-12T15:21:02Z"
  },
  {
    "key": "EWPE7IKA",
    "version": 23,
    "parentItem": "CNUPZBLG",
    "itemType": "attachment",
    "linkMode": "imported_file",
    "title": "Rigby and Bird - 2013 - Convergent contemporary software peer review pract.pdf",
    "accessDate": "",
    "url": "",
    "note": "",
    "contentType": "application/pdf",
    "charset": "",
    "filename": "Rigby and Bird - 2013 - Convergent contemporary software peer review pract.pdf",
    "md5": "34a2bbddac0647c88ac1e108303e1d9d",
    "mtime": 1683904862000,
    "tags": [],
    "relations": {},
    "dateAdded": "2023-05-12T15:21:02Z",
    "dateModified": "2023-05-12T15:21:02Z"
  },
  {
    "key": "FY8XNX75",
    "version": 22,
    "parentItem": "XAHXAVQ3",
    "itemType": "attachment",
    "linkMode": "imported_file",
    "title": "Rigby et al. - 2012 - Contemporary Peer Review in Action Lessons from O.pdf",
    "accessDate": "",
    "url": "",
    "note": "",
    "contentType": "application/pdf",
    "charset": "",
    "filename": "Rigby et al. - 2012 - Contemporary Peer Review in Action Lessons from O.pdf",
    "md5": "321654e50429b12d0ffb18d0ba4a4e68",
    "mtime": 1683904862000,
    "tags": [],
    "relations": {},
    "dateAdded": "2023-05-12T15:21:02Z",
    "dateModified": "2023-05-12T15:21:02Z"
  },
  {
    "key": "ATQNMM9B",
    "version": 21,
    "parentItem": "8I3LNC7I",
    "itemType": "attachment",
    "linkMode": "imported_file",
    "title": "Thongtanunam et al. - 2017 - Review participation in modern code review An emp.pdf",
    "accessDate": "",
    "url": "",
    "note": "",
    "contentType": "application/pdf",
    "charset": "",
    "filename": "Thongtanunam et al. - 2017 - Review participation in modern code review An emp.pdf",
    "md5": "f0c1611299106529dc20e96d47b0e919",
    "mtime": 1683904862000,
    "tags": [],
    "relations": {},
    "dateAdded": "2023-05-12T15:21:02Z",
    "dateModified": "2023-05-12T15:21:02Z"
  },
  {
    "key": "9Z2NAUID",
    "version": 20,
    "parentItem": "BLH5XVAE",
    "itemType": "attachment",
    "linkMode": "imported_file",
    "title": "Eisty and Carver - 2022 - Developers perception of peer code review in resea.pdf",
    "accessDate": "",
    "url": "",
    "note": "",
    "contentType": "application/pdf",
    "charset": "",
    "filename": "Eisty and Carver - 2022 - Developers perception of peer code review in resea.pdf",
    "md5": "002343e15723e84fc1cf2439087ec698",
    "mtime": 1683904862000,
    "tags": [],
    "relations": {},
    "dateAdded": "2023-05-12T15:21:02Z",
    "dateModified": "2023-05-12T15:21:02Z"
  },
  {
    "key": "2NPFJB4Z",
    "version": 16,
    "parentItem": "TZQ9WLX4",
    "itemType": "attachment",
    "linkMode": "imported_url",
    "title": "Zenodo Full Text PDF",
    "accessDate": "2023-05-11T18:49:17Z",
    "url": "https://zenodo.org/record/814220/files/postdoc-survey-full.pdf",
    "note": "",
    "contentType": "application/pdf",
    "charset": "",
    "filename": "Nangia and Katz - 2017 - Track 1 Paper Surveying the U.S. National Postdoc.pdf",
    "md5": "fb480b9041de07022923302ef731aba4",
    "mtime": 1683904862000,
    "tags": [],
    "relations": {},
    "dateAdded": "2023-05-12T15:21:02Z",
    "dateModified": "2023-05-12T15:21:02Z"
  },
  {
    "key": "3ZWUGUNI",
    "version": 15,
    "parentItem": "PPDIPDHT",
    "itemType": "attachment",
    "linkMode": "imported_file",
    "title": "Bhandari Neupane et al. - 2019 - Characterization of Leptazolines A–D, Polar Oxazol.pdf",
    "accessDate": "",
    "url": "",
    "note": "",
    "contentType": "application/pdf",
    "charset": "",
    "filename": "Bhandari Neupane et al. - 2019 - Characterization of Leptazolines A–D, Polar Oxazol.pdf",
    "md5": "ac6de3ef9a037a37538c8ec2787fbcb7",
    "mtime": 1683904862000,
    "tags": [],
    "relations": {},
    "dateAdded": "2023-05-12T15:21:02Z",
    "dateModified": "2023-05-12T15:21:02Z"
  },
  {
    "key": "BLH5XVAE",
    "version": 11,
    "itemType": "journalArticle",
    "title": "Developers perception of peer code review in research software development",
    "creators": [
      {
        "creatorType": "author",
        "firstName": "Nasir U.",
        "lastName": "Eisty"
      },
      {
        "creatorType": "author",
        "firstName": "Jeffrey C.",
        "lastName": "Carver"
      }
    ],
    "abstractNote": "Objective Peer code review is less prevalent in research software than it is in other types of software. In addition, the literature does not contain any studies about the use of peer code review in research software. Therefore, through analyzing developers perceptions, the goal of this work is to understand the current practice of peer code review in the development of research software, identify challenges and barriers associated with peer code review in research software, and present approaches to improve the peer code review in research software.\nMethod We conducted interviews and a community survey of research software developers to collect information about their current peer code review practices, difficulties they face, and how they address those difficulties.\nResults We received 84 unique responses from the interviews and surveys. The results show that while research software teams review a large amount of their code, they lack formal process, proper organization, and adequate people to perform the reviews.\nConclusions Use of peer code review is promising for improving the quality of research software and thereby improving the trustworthiness of the underlying research results. In",
    "publicationTitle": "Empirical Software Engineering",
    "volume": "27",
    "issue": "1",
    "pages": "13",
    "date": "01/2022",
    "series": "",
    "seriesTitle": "",
    "seriesText": "",
    "journalAbbreviation": "Empir Software Eng",
    "language": "en",
    "DOI": "10.1007/s10664-021-10053-x",
    "ISSN": "1382-3256, 1573-7616",
    "shortTitle": "",
    "url": "https://link.springer.com/10.1007/s10664-021-10053-x",
    "accessDate": "2023-05-03T19:39:27Z",
    "archive": "",
    "archiveLocation": "",
    "libraryCatalog": "DOI.org (Crossref)",
    "callNumber": "",
    "rights": "",
    "extra": "",
    "tags": [],
    "collections": [
      "VCTP23NU"
    ],
    "relations": {},
    "dateAdded": "2023-05-12T15:21:02Z",
    "dateModified": "2023-05-12T15:21:02Z"
  },
  {
    "key": "PPDIPDHT",
    "version": 11,
    "itemType": "journalArticle",
    "title": "Characterization of Leptazolines A–D, Polar Oxazolines from the Cyanobacterium <i>Leptolyngbya</i> sp., Reveals a Glitch with the “Willoughby–Hoye” Scripts for Calculating NMR Chemical Shifts",
    "creators": [
      {
        "creatorType": "author",
        "firstName": "Jayanti",
        "lastName": "Bhandari Neupane"
      },
      {
        "creatorType": "author",
        "firstName": "Ram P.",
        "lastName": "Neupane"
      },
      {
        "creatorType": "author",
        "firstName": "Yuheng",
        "lastName": "Luo"
      },
      {
        "creatorType": "author",
        "firstName": "Wesley Y.",
        "lastName": "Yoshida"
      },
      {
        "creatorType": "author",
        "firstName": "Rui",
        "lastName": "Sun"
      },
      {
        "creatorType": "author",
        "firstName": "Philip G.",
        "lastName": "Williams"
      }
    ],
    "abstractNote": "The bioactivity-guided examination of a Leptolyngbya sp. led to the isolation of leptazolines A−D (1−4), from the culture media, along with two degradation products (5 and 6). Density functional theory nuclear magnetic resonance calculations established the relative conﬁgurations of 1 and 2 and revealed that the calculated shifts depended on the operating system when using the “Willoughby−Hoye” Python scripts to streamline the processing of the output ﬁles, a previously unrecognized ﬂaw that could lead to incorrect conclusions.",
    "publicationTitle": "Organic Letters",
    "volume": "21",
    "issue": "20",
    "pages": "8449-8453",
    "date": "2019-10-18",
    "series": "",
    "seriesTitle": "",
    "seriesText": "",
    "journalAbbreviation": "Org. Lett.",
    "language": "en",
    "DOI": "10.1021/acs.orglett.9b03216",
    "ISSN": "1523-7060, 1523-7052",
    "shortTitle": "",
    "url": "https://pubs.acs.org/doi/10.1021/acs.orglett.9b03216",
    "accessDate": "2023-05-05T13:51:47Z",
    "archive": "",
    "archiveLocation": "",
    "libraryCatalog": "DOI.org (Crossref)",
    "callNumber": "",
    "rights": "",
    "extra": "",
    "tags": [],
    "collections": [
      "VCTP23NU"
    ],
    "relations": {},
    "dateAdded": "2023-05-12T15:21:02Z",
    "dateModified": "2023-05-12T15:21:02Z"
  },
  {
    "key": "Y3HY74M3",
    "version": 10,
    "itemType": "journalArticle",
    "title": "Design and code inspections to reduce errors in program development",
    "creators": [
      {
        "creatorType": "author",
        "firstName": "Michael E",
        "lastName": "Fagan"
      }
    ],
    "abstractNote": "",
    "publicationTitle": "IBM Systems Journal",
    "volume": "15",
    "issue": "3",
    "pages": "182-211",
    "date": "1976",
    "series": "",
    "seriesTitle": "",
    "seriesText": "",
    "journalAbbreviation": "IBM SYST J",
    "language": "en",
    "DOI": "",
    "ISSN": "",
    "shortTitle": "",
    "url": "",
    "accessDate": "",
    "archive": "",
    "archiveLocation": "",
    "libraryCatalog": "Zotero",
    "callNumber": "",
    "rights": "",
    "extra": "",
    "tags": [],
    "collections": [
      "VCTP23NU"
    ],
    "relations": {},
    "dateAdded": "2023-05-12T15:21:02Z",
    "dateModified": "2023-05-12T15:21:02Z"
  },
  {
    "key": "8I3LNC7I",
    "version": 10,
    "itemType": "journalArticle",
    "title": "Review participation in modern code review: An empirical study of the android, Qt, and OpenStack projects",
    "creators": [
      {
        "creatorType": "author",
        "firstName": "Patanamon",
        "lastName": "Thongtanunam"
      },
      {
        "creatorType": "author",
        "firstName": "Shane",
        "lastName": "McIntosh"
      },
      {
        "creatorType": "author",
        "firstName": "Ahmed E.",
        "lastName": "Hassan"
      },
      {
        "creatorType": "author",
        "firstName": "Hajimu",
        "lastName": "Iida"
      }
    ],
    "abstractNote": "",
    "publicationTitle": "Empirical Software Engineering",
    "volume": "22",
    "issue": "2",
    "pages": "768-817",
    "date": "4/2017",
    "series": "",
    "seriesTitle": "",
    "seriesText": "",
    "journalAbbreviation": "Empir Software Eng",
    "language": "en",
    "DOI": "10.1007/s10664-016-9452-6",
    "ISSN": "1382-3256, 1573-7616",
    "shortTitle": "Review participation in modern code review",
    "url": "http://link.springer.com/10.1007/s10664-016-9452-6",
    "accessDate": "2023-05-04T19:17:32Z",
    "archive": "",
    "archiveLocation": "",
    "libraryCatalog": "DOI.org (Crossref)",
    "callNumber": "",
    "rights": "",
    "extra": "",
    "tags": [],
    "collections": [
      "VCTP23NU"
    ],
    "relations": {},
    "dateAdded": "2023-05-12T15:21:02Z",
    "dateModified": "2023-05-12T15:21:02Z"
  },
  {
    "key": "8FQP6RHM",
    "version": 10,
    "parentItem": "TZQ9WLX4",
    "itemType": "note",
    "note": "This paper was submitted to WSSSPE5.1 - http://wssspe.researchcomputing.org.uk/wssspe5-1/\nThe final accepted version is https://doi.org/10.6084/m9.figshare.5328442",
    "tags": [],
    "relations": {},
    "dateAdded": "2023-05-12T15:21:02Z",
    "dateModified": "2023-05-12T15:21:02Z"
  },
  {
    "key": "CNUPZBLG",
    "version": 10,
    "itemType": "conferencePaper",
    "title": "Convergent contemporary software peer review practices",
    "creators": [
      {
        "creatorType": "author",
        "firstName": "Peter C.",
        "lastName": "Rigby"
      },
      {
        "creatorType": "author",
        "firstName": "Christian",
        "lastName": "Bird"
      }
    ],
    "abstractNote": "Software peer review is practiced on a diverse set of software projects that have drastically diﬀerent settings, cultures, incentive systems, and time pressures. In an eﬀort to characterize and understand these diﬀerences we examine two Google-led projects, Android and Chromium OS, three Microsoft projects, Bing, Oﬃce, and MS SQL, and projects internal to AMD. We contrast our ﬁndings with data taken from traditional software inspection conducted on a Lucent project and from open source software peer review on six projects, including Apache, Linux, and KDE. Our measures of interest include the review interval, the number of developers involved in review, and proxy measures for the number of defects found during review. We ﬁnd that despite diﬀerences among projects, many of the characteristics of the review process have independently converged to similar values which we think indicate general principles of code review practice. We also introduce a measure of the degree to which knowledge is shared during review. This is an aspect of review practice that has traditionally only had experiential support. Our knowledge sharing measure shows that conducting peer review increases the number of distinct ﬁles a developer knows about by 66% to 150% depending on the project. This paper is one of the ﬁrst studies of contemporary review in software ﬁrms and the most diverse study of peer review to date.",
    "date": "2013-08-18",
    "proceedingsTitle": "Proceedings of the 2013 9th Joint Meeting on Foundations of Software Engineering",
    "conferenceName": "ESEC/FSE'13: Joint Meeting of the European Software Engineering Conference and the ACM SIGSOFT Symposium on the Foundations of Software Engineering",
    "place": "Saint Petersburg Russia",
    "publisher": "ACM",
    "volume": "",
    "pages": "202-212",
    "series": "",
    "language": "en",
    "DOI": "10.1145/2491411.2491444",
    "ISBN": "978-1-4503-2237-9",
    "shortTitle": "",
    "url": "https://dl.acm.org/doi/10.1145/2491411.2491444",
    "accessDate": "2023-05-04T21:00:24Z",
    "archive": "",
    "archiveLocation": "",
    "libraryCatalog": "DOI.org (Crossref)",
    "callNumber": "",
    "rights": "",
    "extra": "",
    "tags": [],
    "collections": [
      "VCTP23NU"
    ],
    "relations": {},
    "dateAdded": "2023-05-12T15:21:02Z",
    "dateModified": "2023-05-12T15:21:02Z"
  }
]
